pykattis.py
pykattis/__init__.py
pykattis/solution_template.py
pykattis-0.0.3.dist-info/METADATA
pykattis-0.0.3.dist-info/RECORD
pykattis-0.0.3.dist-info/WHEEL
pykattis-0.0.3.dist-info/entry_points.txt
pykattis-0.0.3.dist-info/top_level.txt
