Metadata-Version: 2.1
Name: pykattis
Version: 0.0.3
Summary: A CLI tool for solving Kattis problems with python.
Home-page: https://github.com/joelhed/pykattis
Author: Joel Hedtjärn
Author-email: joel.hedtjarn@gmail.com
License: MIT
Platform: UNKNOWN
Classifier: License :: OSI Approved :: MIT License
Classifier: Programming Language :: Python
Classifier: Programming Language :: Python :: 3
Classifier: Programming Language :: Python :: 3.6
Classifier: Programming Language :: Python :: Implementation :: CPython
Classifier: Programming Language :: Python :: Implementation :: PyPy
Requires-Python: >=3.6.0
Requires-Dist: requests
